{"farezone":"9","closed":false,"departures":[{"stop_id":"1177","service_id":"507","direction":"outbound","operator":"UZM","origin":{"stop_id":"1177","name":"ParaparaumuColl (Sc"},"destination":{"stop_id":"1500","name":"School Bus"},"delay":"PT0S","vehicle_id":"","name":"ParaparaumuColl (Sc","arrival":{"aimed":"","expected":""},"departure":{"aimed":"2021-02-18T15:20:00+13:00","expected":null},"status":"","wheelchair_accessible":false},{"stop_id":"1177","service_id":"508","direction":"outbound","operator":"UZM","origin":{"stop_id":"1177","name":"ParaparaumuColl (Sc"},"destination":{"stop_id":"1530","name":"School Bus"},"delay":"PT0S","vehicle_id":"","name":"ParaparaumuColl (Sc","arrival":{"aimed":"","expected":""},"departure":{"aimed":"2021-02-18T15:20:00+13:00","expected":null},"status":"","wheelchair_accessible":false},{"stop_id":"1177","service_id":"510","direction":"outbound","operator":"UZM","origin":{"stop_id":"1177","name":"ParaparaumuColl (Sc"},"destination":{"stop_id":"1560","name":"School Bus"},"delay":"PT0S","vehicle_id":"","name":"ParaparaumuColl (Sc","arrival":{"aimed":"","expected":""},"departure":{"aimed":"2021-02-18T15:20:00+13:00","expected":null},"status":"","wheelchair_accessible":false}],"alerts":[]}