{"farezone":"10","closed":false,"departures":[{"stop_id":"1608","service_id":"280","direction":"outbound","operator":"UZM","origin":{"stop_id":"1501","name":"WaikanaeStn-MainRd"},"destination":{"stop_id":"1501","name":"Waikanae"},"delay":"PT2M11S","vehicle_id":"9006","name":"FieldWay at William","arrival":{"aimed":"2021-02-17T17:13:00+13:00","expected":"2021-02-17T17:15:11+13:00"},"departure":{"aimed":"2021-02-17T17:13:00+13:00","expected":"2021-02-17T17:15:11+13:00"},"status":"delayed","wheelchair_accessible":true},{"stop_id":"1608","service_id":"280","direction":"outbound","operator":"UZM","origin":{"stop_id":"1501","name":"WaikanaeStn-MainRd"},"destination":{"stop_id":"1501","name":"Waikanae"},"delay":"PT1M50S","vehicle_id":"9009","name":"FieldWay at William","arrival":{"aimed":"2021-02-17T17:33:00+13:00","expected":"2021-02-17T17:34:50+13:00"},"departure":{"aimed":"2021-02-17T17:33:00+13:00","expected":"2021-02-17T17:34:50+13:00"},"status":"ontime","wheelchair_accessible":true},{"stop_id":"1608","service_id":"280","direction":"outbound","operator":"UZM","origin":{"stop_id":"1501","name":"WaikanaeStn-MainRd"},"destination":{"stop_id":"1501","name":"Waikanae"},"delay":"PT1M50S","vehicle_id":"9014","name":"FieldWay at William","arrival":{"aimed":"2021-02-17T17:53:00+13:00","expected":"2021-02-17T17:54:50+13:00"},"departure":{"aimed":"2021-02-17T17:53:00+13:00","expected":"2021-02-17T17:54:50+13:00"},"status":"ontime","wheelchair_accessible":true},{"stop_id":"1608","service_id":"280","direction":"outbound","operator":"UZM","origin":{"stop_id":"1501","name":"WaikanaeStn-MainRd"},"destination":{"stop_id":"1501","name":"Waikanae"},"delay":"PT0S","vehicle_id":"","name":"FieldWay at William","arrival":{"aimed":"2021-02-17T18:13:00+13:00","expected":""},"departure":{"aimed":"2021-02-17T18:13:00+13:00","expected":null},"status":"","wheelchair_accessible":false},{"stop_id":"1608","service_id":"280","direction":"outbound","operator":"UZM","origin":{"stop_id":"1501","name":"WaikanaeStn-MainRd"},"destination":{"stop_id":"1501","name":"Waikanae"},"delay":"PT0S","vehicle_id":"","name":"FieldWay at William","arrival":{"aimed":"2021-02-17T18:35:00+13:00","expected":""},"departure":{"aimed":"2021-02-17T18:35:00+13:00","expected":null},"status":"","wheelchair_accessible":false},{"stop_id":"1608","service_id":"280","direction":"outbound","operator":"UZM","origin":{"stop_id":"1501","name":"WaikanaeStn-MainRd"},"destination":{"stop_id":"1501","name":"Waikanae"},"delay":"PT0S","vehicle_id":"","name":"FieldWay at William","arrival":{"aimed":"2021-02-17T18:53:00+13:00","expected":""},"departure":{"aimed":"2021-02-17T18:53:00+13:00","expected":null},"status":"","wheelchair_accessible":false},{"stop_id":"1608","service_id":"280","direction":"outbound","operator":"UZM","origin":{"stop_id":"1501","name":"WaikanaeStn-MainRd"},"destination":{"stop_id":"1501","name":"Waikanae"},"delay":"PT0S","vehicle_id":"","name":"FieldWay at William","arrival":{"aimed":"2021-02-17T19:17:00+13:00","expected":""},"departure":{"aimed":"2021-02-17T19:17:00+13:00","expected":null},"status":"","wheelchair_accessible":false},{"stop_id":"1608","service_id":"280","direction":"outbound","operator":"UZM","origin":{"stop_id":"1501","name":"WaikanaeStn-MainRd"},"destination":{"stop_id":"1501","name":"Waikanae"},"delay":"PT0S","vehicle_id":"","name":"FieldWay at William","arrival":{"aimed":"2021-02-17T19:38:00+13:00","expected":""},"departure":{"aimed":"2021-02-17T19:38:00+13:00","expected":null},"status":"","wheelchair_accessible":false},{"stop_id":"1608","service_id":"280","direction":"outbound","operator":"UZM","origin":{"stop_id":"1501","name":"WaikanaeStn-MainRd"},"destination":{"stop_id":"1501","name":"Waikanae"},"delay":"PT0S","vehicle_id":"","name":"FieldWay at William","arrival":{"aimed":"2021-02-17T20:38:00+13:00","expected":""},"departure":{"aimed":"2021-02-17T20:38:00+13:00","expected":null},"status":"","wheelchair_accessible":false},{"stop_id":"1608","service_id":"280","direction":"outbound","operator":"UZM","origin":{"stop_id":"1501","name":"WaikanaeStn-MainRd"},"destination":{"stop_id":"1501","name":"Waikanae"},"delay":"PT0S","vehicle_id":"","name":"FieldWay at William","arrival":{"aimed":"2021-02-17T21:38:00+13:00","expected":""},"departure":{"aimed":"2021-02-17T21:38:00+13:00","expected":null},"status":"","wheelchair_accessible":false},{"stop_id":"1608","service_id":"280","direction":"outbound","operator":"UZM","origin":{"stop_id":"1501","name":"WaikanaeStn-MainRd"},"destination":{"stop_id":"1501","name":"Waikanae"},"delay":"PT0S","vehicle_id":"","name":"FieldWay at William","arrival":{"aimed":"2021-02-18T05:38:00+13:00","expected":""},"departure":{"aimed":"2021-02-18T05:38:00+13:00","expected":null},"status":"","wheelchair_accessible":false},{"stop_id":"1608","service_id":"280","direction":"outbound","operator":"UZM","origin":{"stop_id":"1501","name":"WaikanaeStn-MainRd"},"destination":{"stop_id":"1501","name":"Waikanae"},"delay":"PT0S","vehicle_id":"","name":"FieldWay at William","arrival":{"aimed":"2021-02-18T06:08:00+13:00","expected":""},"departure":{"aimed":"2021-02-18T06:08:00+13:00","expected":null},"status":"","wheelchair_accessible":false},{"stop_id":"1608","service_id":"280","direction":"outbound","operator":"UZM","origin":{"stop_id":"1501","name":"WaikanaeStn-MainRd"},"destination":{"stop_id":"1501","name":"Waikanae"},"delay":"PT0S","vehicle_id":"","name":"FieldWay at William","arrival":{"aimed":"2021-02-18T06:38:00+13:00","expected":""},"departure":{"aimed":"2021-02-18T06:38:00+13:00","expected":null},"status":"","wheelchair_accessible":false},{"stop_id":"1608","service_id":"280","direction":"outbound","operator":"UZM","origin":{"stop_id":"1501","name":"WaikanaeStn-MainRd"},"destination":{"stop_id":"1501","name":"Waikanae"},"delay":"PT0S","vehicle_id":"","name":"FieldWay at William","arrival":{"aimed":"2021-02-18T06:58:00+13:00","expected":""},"departure":{"aimed":"2021-02-18T06:58:00+13:00","expected":null},"status":"","wheelchair_accessible":false},{"stop_id":"1608","service_id":"280","direction":"outbound","operator":"UZM","origin":{"stop_id":"1501","name":"WaikanaeStn-MainRd"},"destination":{"stop_id":"1501","name":"Waikanae"},"delay":"PT0S","vehicle_id":"","name":"FieldWay at William","arrival":{"aimed":"2021-02-18T07:17:00+13:00","expected":""},"departure":{"aimed":"2021-02-18T07:17:00+13:00","expected":null},"status":"","wheelchair_accessible":false},{"stop_id":"1608","service_id":"280","direction":"outbound","operator":"UZM","origin":{"stop_id":"1501","name":"WaikanaeStn-MainRd"},"destination":{"stop_id":"1501","name":"Waikanae"},"delay":"PT0S","vehicle_id":"","name":"FieldWay at William","arrival":{"aimed":"2021-02-18T07:39:00+13:00","expected":""},"departure":{"aimed":"2021-02-18T07:39:00+13:00","expected":null},"status":"","wheelchair_accessible":false},{"stop_id":"1608","service_id":"280","direction":"outbound","operator":"UZM","origin":{"stop_id":"1501","name":"WaikanaeStn-MainRd"},"destination":{"stop_id":"1501","name":"Waikanae"},"delay":"PT0S","vehicle_id":"","name":"FieldWay at William","arrival":{"aimed":"2021-02-18T08:04:00+13:00","expected":""},"departure":{"aimed":"2021-02-18T08:04:00+13:00","expected":null},"status":"","wheelchair_accessible":false},{"stop_id":"1608","service_id":"280","direction":"outbound","operator":"UZM","origin":{"stop_id":"1501","name":"WaikanaeStn-MainRd"},"destination":{"stop_id":"1501","name":"Waikanae"},"delay":"PT0S","vehicle_id":"","name":"FieldWay at William","arrival":{"aimed":"2021-02-18T08:18:00+13:00","expected":""},"departure":{"aimed":"2021-02-18T08:18:00+13:00","expected":null},"status":"","wheelchair_accessible":false},{"stop_id":"1608","service_id":"505","direction":"inbound","operator":"UZM","origin":{"stop_id":"1535","name":"HuiawaSt at Hemara"},"destination":{"stop_id":"1203","name":"School Bus"},"delay":"PT0S","vehicle_id":"","name":"FieldWay at William","arrival":{"aimed":"2021-02-18T08:28:00+13:00","expected":""},"departure":{"aimed":"2021-02-18T08:28:00+13:00","expected":null},"status":"","wheelchair_accessible":false},{"stop_id":"1608","service_id":"280","direction":"outbound","operator":"UZM","origin":{"stop_id":"1501","name":"WaikanaeStn-MainRd"},"destination":{"stop_id":"1501","name":"Waikanae"},"delay":"PT0S","vehicle_id":"","name":"FieldWay at William","arrival":{"aimed":"2021-02-18T08:38:00+13:00","expected":""},"departure":{"aimed":"2021-02-18T08:38:00+13:00","expected":null},"status":"","wheelchair_accessible":false}],"alerts":[]}