{"farezone":"4","closed":false,"departures":[{"stop_id":"3956","service_id":"60","direction":"inbound","operator":"MNM","origin":{"stop_id":"2002","name":"PoriruaStn-B"},"destination":{"stop_id":"3081","name":"Johnsonville"},"delay":"-PT42S","vehicle_id":"7501","name":"TawaMall-MainRd (20","arrival":{"aimed":"2021-02-17T17:11:00+13:00","expected":"2021-02-17T17:10:18+13:00"},"departure":{"aimed":"2021-02-17T17:11:00+13:00","expected":"2021-02-17T17:11:00+13:00"},"status":"ontime","wheelchair_accessible":true},{"stop_id":"3956","service_id":"60","direction":"inbound","operator":"MNM","origin":{"stop_id":"2002","name":"PoriruaStn-B"},"destination":{"stop_id":"3081","name":"Johnsonville"},"delay":"PT18S","vehicle_id":"7167","name":"TawaMall-MainRd (20","arrival":{"aimed":"2021-02-17T17:23:00+13:00","expected":"2021-02-17T17:23:18+13:00"},"departure":{"aimed":"2021-02-17T17:23:00+13:00","expected":"2021-02-17T17:23:18+13:00"},"status":"ontime","wheelchair_accessible":true},{"stop_id":"3956","service_id":"60","direction":"inbound","operator":"MNM","origin":{"stop_id":"2002","name":"PoriruaStn-B"},"destination":{"stop_id":"3081","name":"Johnsonville"},"delay":"PT18S","vehicle_id":"7155","name":"TawaMall-MainRd (20","arrival":{"aimed":"2021-02-17T17:53:00+13:00","expected":"2021-02-17T17:53:18+13:00"},"departure":{"aimed":"2021-02-17T17:53:00+13:00","expected":"2021-02-17T17:53:18+13:00"},"status":"ontime","wheelchair_accessible":true},{"stop_id":"3956","service_id":"60","direction":"inbound","operator":"MNM","origin":{"stop_id":"2002","name":"PoriruaStn-B"},"destination":{"stop_id":"3081","name":"Johnsonville"},"delay":"PT0S","vehicle_id":"","name":"TawaMall-MainRd (20","arrival":{"aimed":"2021-02-17T18:10:00+13:00","expected":""},"departure":{"aimed":"2021-02-17T18:10:00+13:00","expected":null},"status":"","wheelchair_accessible":false},{"stop_id":"3956","service_id":"60","direction":"inbound","operator":"MNM","origin":{"stop_id":"2002","name":"PoriruaStn-B"},"destination":{"stop_id":"3081","name":"Johnsonville"},"delay":"PT0S","vehicle_id":"","name":"TawaMall-MainRd (20","arrival":{"aimed":"2021-02-17T18:23:00+13:00","expected":""},"departure":{"aimed":"2021-02-17T18:23:00+13:00","expected":null},"status":"","wheelchair_accessible":false},{"stop_id":"3956","service_id":"60","direction":"inbound","operator":"MNM","origin":{"stop_id":"2002","name":"PoriruaStn-B"},"destination":{"stop_id":"3081","name":"Johnsonville"},"delay":"PT0S","vehicle_id":"","name":"TawaMall-MainRd (20","arrival":{"aimed":"2021-02-17T19:06:00+13:00","expected":""},"departure":{"aimed":"2021-02-17T19:06:00+13:00","expected":null},"status":"","wheelchair_accessible":false},{"stop_id":"3956","service_id":"60","direction":"inbound","operator":"MNM","origin":{"stop_id":"2002","name":"PoriruaStn-B"},"destination":{"stop_id":"3081","name":"Johnsonville"},"delay":"PT0S","vehicle_id":"","name":"TawaMall-MainRd (20","arrival":{"aimed":"2021-02-17T20:15:00+13:00","expected":""},"departure":{"aimed":"2021-02-17T20:15:00+13:00","expected":null},"status":"","wheelchair_accessible":false},{"stop_id":"3956","service_id":"60","direction":"inbound","operator":"MNM","origin":{"stop_id":"2002","name":"PoriruaStn-B"},"destination":{"stop_id":"3081","name":"Johnsonville"},"delay":"PT0S","vehicle_id":"","name":"TawaMall-MainRd (20","arrival":{"aimed":"2021-02-17T21:11:00+13:00","expected":""},"departure":{"aimed":"2021-02-17T21:11:00+13:00","expected":null},"status":"","wheelchair_accessible":false},{"stop_id":"3956","service_id":"60e","direction":"inbound","operator":"MNM","origin":{"stop_id":"2002","name":"PoriruaStn-B"},"destination":{"stop_id":"5516","name":"Courtenay Pl"},"delay":"PT0S","vehicle_id":"","name":"TawaMall-MainRd (20","arrival":{"aimed":"2021-02-18T06:37:00+13:00","expected":""},"departure":{"aimed":"2021-02-18T06:37:00+13:00","expected":null},"status":"","wheelchair_accessible":false},{"stop_id":"3956","service_id":"60e","direction":"inbound","operator":"MNM","origin":{"stop_id":"2002","name":"PoriruaStn-B"},"destination":{"stop_id":"5516","name":"Courtenay Pl"},"delay":"PT0S","vehicle_id":"","name":"TawaMall-MainRd (20","arrival":{"aimed":"2021-02-18T06:57:00+13:00","expected":""},"departure":{"aimed":"2021-02-18T06:57:00+13:00","expected":null},"status":"","wheelchair_accessible":false},{"stop_id":"3956","service_id":"60e","direction":"inbound","operator":"MNM","origin":{"stop_id":"2002","name":"PoriruaStn-B"},"destination":{"stop_id":"6553","name":"Courtenay Pl\/St Pat"},"delay":"PT0S","vehicle_id":"","name":"TawaMall-MainRd (20","arrival":{"aimed":"2021-02-18T07:17:00+13:00","expected":""},"departure":{"aimed":"2021-02-18T07:17:00+13:00","expected":null},"status":"","wheelchair_accessible":false},{"stop_id":"3956","service_id":"60e","direction":"inbound","operator":"MNM","origin":{"stop_id":"2002","name":"PoriruaStn-B"},"destination":{"stop_id":"5516","name":"Courtenay Pl"},"delay":"PT0S","vehicle_id":"","name":"TawaMall-MainRd (20","arrival":{"aimed":"2021-02-18T07:37:00+13:00","expected":""},"departure":{"aimed":"2021-02-18T07:37:00+13:00","expected":null},"status":"","wheelchair_accessible":false},{"stop_id":"3956","service_id":"60e","direction":"inbound","operator":"MNM","origin":{"stop_id":"2002","name":"PoriruaStn-B"},"destination":{"stop_id":"5516","name":"Courtenay Pl"},"delay":"PT0S","vehicle_id":"","name":"TawaMall-MainRd (20","arrival":{"aimed":"2021-02-18T07:57:00+13:00","expected":""},"departure":{"aimed":"2021-02-18T07:57:00+13:00","expected":null},"status":"","wheelchair_accessible":false},{"stop_id":"3956","service_id":"60","direction":"inbound","operator":"MNM","origin":{"stop_id":"2002","name":"PoriruaStn-B"},"destination":{"stop_id":"3081","name":"Johnsonville"},"delay":"PT0S","vehicle_id":"","name":"TawaMall-MainRd (20","arrival":{"aimed":"2021-02-18T08:10:00+13:00","expected":""},"departure":{"aimed":"2021-02-18T08:10:00+13:00","expected":null},"status":"","wheelchair_accessible":false},{"stop_id":"3956","service_id":"60","direction":"inbound","operator":"MNM","origin":{"stop_id":"2002","name":"PoriruaStn-B"},"destination":{"stop_id":"3081","name":"Johnsonville"},"delay":"PT0S","vehicle_id":"","name":"TawaMall-MainRd (20","arrival":{"aimed":"2021-02-18T08:17:00+13:00","expected":""},"departure":{"aimed":"2021-02-18T08:17:00+13:00","expected":null},"status":"","wheelchair_accessible":false},{"stop_id":"3956","service_id":"60","direction":"inbound","operator":"MNM","origin":{"stop_id":"2002","name":"PoriruaStn-B"},"destination":{"stop_id":"3081","name":"Johnsonville"},"delay":"PT0S","vehicle_id":"","name":"TawaMall-MainRd (20","arrival":{"aimed":"2021-02-18T08:27:00+13:00","expected":""},"departure":{"aimed":"2021-02-18T08:27:00+13:00","expected":null},"status":"","wheelchair_accessible":false},{"stop_id":"3956","service_id":"60","direction":"inbound","operator":"MNM","origin":{"stop_id":"2002","name":"PoriruaStn-B"},"destination":{"stop_id":"3081","name":"Johnsonville"},"delay":"PT0S","vehicle_id":"","name":"TawaMall-MainRd (20","arrival":{"aimed":"2021-02-18T08:37:00+13:00","expected":""},"departure":{"aimed":"2021-02-18T08:37:00+13:00","expected":null},"status":"","wheelchair_accessible":false},{"stop_id":"3956","service_id":"60","direction":"inbound","operator":"MNM","origin":{"stop_id":"2002","name":"PoriruaStn-B"},"destination":{"stop_id":"3081","name":"Johnsonville"},"delay":"PT0S","vehicle_id":"","name":"TawaMall-MainRd (20","arrival":{"aimed":"2021-02-18T09:02:00+13:00","expected":""},"departure":{"aimed":"2021-02-18T09:02:00+13:00","expected":null},"status":"","wheelchair_accessible":false},{"stop_id":"3956","service_id":"60","direction":"inbound","operator":"MNM","origin":{"stop_id":"2002","name":"PoriruaStn-B"},"destination":{"stop_id":"3081","name":"Johnsonville"},"delay":"PT0S","vehicle_id":"","name":"TawaMall-MainRd (20","arrival":{"aimed":"2021-02-18T09:22:00+13:00","expected":""},"departure":{"aimed":"2021-02-18T09:22:00+13:00","expected":null},"status":"","wheelchair_accessible":false},{"stop_id":"3956","service_id":"60","direction":"inbound","operator":"MNM","origin":{"stop_id":"2002","name":"PoriruaStn-B"},"destination":{"stop_id":"3081","name":"Johnsonville"},"delay":"PT0S","vehicle_id":"","name":"TawaMall-MainRd (20","arrival":{"aimed":"2021-02-18T09:42:00+13:00","expected":""},"departure":{"aimed":"2021-02-18T09:42:00+13:00","expected":null},"status":"","wheelchair_accessible":false}],"alerts":[]}